nlpcv/__init__.py
nlpcv/vulcan.py
nlpcv/vision/__init__.py
nlpcv/vision/metainfo.py
nlpcv-0.0.1.dist-info/LICENSE
nlpcv-0.0.1.dist-info/METADATA
nlpcv-0.0.1.dist-info/WHEEL
nlpcv-0.0.1.dist-info/top_level.txt
nlpcv-0.0.1.dist-info/RECORD
